BigSur/__init__.py
BigSur/feature_selection.py
BigSur/preprocessing.py
BigSur/synthetic_data.py
bigsur-0.0.4.dist-info/licenses/LICENSE
bigsur-0.0.4.dist-info/METADATA
bigsur-0.0.4.dist-info/WHEEL
bigsur-0.0.4.dist-info/top_level.txt
bigsur-0.0.4.dist-info/RECORD
