Metadata-Version: 2.4
Name: bigsur
Version: 0.0.4
Summary: Basic Informatics and Gene Statistics from Unnormalized Reads, a feature selection tool for scRNAseq
Home-page: https://github.com/landerlabcode/BigSur
Author: Emmanuel Dollinger
Author-email: Emmanuel Dollinger <edolling@uci.edu>
License-Expression: MIT
Project-URL: Homepage, https://github.com/landerlabcode/BigSur/
Project-URL: Issues, https://github.com/landerlabcode/BigSur/issues
Classifier: Programming Language :: Python :: 3
Classifier: Operating System :: OS Independent
Requires-Python: >=3.9, <4
License-File: LICENSE
Dynamic: author
Dynamic: home-page
Dynamic: license-file
Dynamic: requires-python
